arlo.py
eventstream.py
request.py
arlo-1.2.64.dist-info/LICENSE
arlo-1.2.64.dist-info/METADATA
arlo-1.2.64.dist-info/WHEEL
arlo-1.2.64.dist-info/top_level.txt
arlo-1.2.64.dist-info/RECORD
