Metadata-Version: 2.1
Name: arlo
Version: 1.2.64
Summary: Python Arlo is a library written in Python 2.7/3x which exposes the Netgear Arlo cameras via the apis that are consumed by their website.
Home-page: https://github.com/jeffreydwalter/arlo
Author: Jeffrey D. Walter
Author-email: jeffreydwalter@gmail.com
License: Apache Software License
Keywords: arlo,camera,home automation,netgear,python
Classifier: Development Status :: 5 - Production/Stable
Classifier: Environment :: Other Environment
Classifier: Intended Audience :: Developers
Classifier: License :: OSI Approved :: Apache Software License
Classifier: Operating System :: OS Independent
Classifier: Programming Language :: Python
Classifier: Programming Language :: Python :: 3.4
Classifier: Programming Language :: Python :: 3.5
Classifier: Programming Language :: Python :: 3.6
Classifier: Programming Language :: Python :: 3.7
Classifier: Programming Language :: Python :: 3.8
Classifier: Programming Language :: Python :: 3.9
Classifier: Topic :: Software Development :: Libraries :: Python Modules
License-File: LICENSE
Requires-Dist: monotonic
Requires-Dist: requests
Requires-Dist: responses (==0.10.15)
Requires-Dist: urllib3 (==1.24)
Requires-Dist: sseclient (==0.0.22)
Requires-Dist: PySocks
Requires-Dist: pickle-mixin
Requires-Dist: google-api-python-client
Requires-Dist: google-auth-oauthlib
